async_vk_bots/__init__.py
async_vk_bots/api/__init__.py
async_vk_bots/api/API.py
async_vk_bots/api/APIError.py
async_vk_bots/api/CarouselMaker.py
async_vk_bots/api/KeyboardMaker.py
async_vk_bots/api/LongPoll.py
async_vk_bots/Bot.py
async_vk_bots/ext/commands.py
async_vk_bots/ext/Context.py
async_vk_bots/ext/Scenario.py
async_vk_bots-0.1.5.dist-info/LICENSE
async_vk_bots-0.1.5.dist-info/WHEEL
async_vk_bots-0.1.5.dist-info/METADATA
async_vk_bots-0.1.5.dist-info/RECORD
